{"indicator":"6.5.2","layout":"indicator","permalink":"/6-5-2/","sdg_goal":"6","target_id":"6.5","published":true,"target":"2030\ub144\uae4c\uc9c0 \uad6d\uacbd \uac04 \ud611\ub825\uc744 \ud3ec\ud568\ud558\uc5ec \ud1b5\ud569\ub41c \ubb3c \uc790\uc6d0 \uad00\ub9ac \uc774\ud589","indicator_name":"\ubb3c \ud611\ub825\uc744 \uc704\ud55c \uc6b4\uc601\ud611\uc815\uc744 \ub9fa\uace0 \uc788\ub294 \uc811\uacbd \uc9c0\uc5ed \ube44\uc728","indicator_definition":"\ud55c \uad6d\uac00 \ub0b4\uc5d0\uc11c \ubb3c \ud611\ub825\uc744 \uc704\ud55c \uc6b4\uc601\ud611\uc815\uc744 \ub9fa\uace0 \uc788\ub294 \uc811\uacbd \uc9c0\uc5ed\uc758 \ube44\uc728 \uc774\ub294 \uad6d\uac00\uc758 \uc811\uacbd \uc9c0\ud45c\uc218 \uc720\uc5ed\uacfc \uc811\uacbd \ub300\uc218\uce35(\uc989, \u2018\uc811\uacbd \uc9c0\uc5ed\u2019)\uc758 \ud45c\uba74\uc801 \uc911 \uc6b4\uc601\ud611\uc815\uc5d0 \uc758\ud574 \ubcf4\ud638\ub418\ub294 \uc9c0\uc5ed\uc758 \ud574\ub2f9 \uba74\uc801\uc744 \ud574\ub2f9 \uad6d\uac00\uc758 \ubaa8\ub4e0 \uc811\uacbd \uc9c0\uc5ed(\uc9c0\ud45c\uc218\uc640 \ub300\uc218\uce35\uc744 \ud3ec\ud568)\uc758 \ucd1d \uba74\uc801\uc758 \ud569\uc73c\ub85c \ub098\ub204\uc5b4 \uc0b0\ucd9c\ud568","un_designated_tier":"I","un_custodian_agency":"United Nations Education and Scientific Cultural Organisation - Institute for Statistics (UNESCO-UIS), United Nations Economic Commission for Europe (UNECE)","goal_meta_link":"https://unstats.un.org/sdgs/metadata/files/Metadata-06-05-02.pdf","goal_meta_link_text":"https://unstats.un.org/sdgs/metadata/files/Metadata-06-05-02.pdf","goal_meta_local_link":"https://kostat-sdg-kor.github.io/sdg-indicators/public/data/Metadata-06-05-02_KOR.pdf","goal_meta_local_link_text":"https://kostat-sdg-kor.github.io/sdg-indicators/public/data/Metadata-06-05-02_KOR.pdf","national_geographical_coverage":"\uc804\uccb4","reporting_status":"complete","data_non_statistical":false,"graph_type":"bar","data_show_map":false,"data_keywords":"DEFRA","source_active_1":false,"source_active_2":false,"source_active_3":false,"source_active_4":false,"source_active_5":false,"source_active_6":false,"indicator_sort_order":"06-05-02","source_url_text_1":"Link to source","source_url_text_2":"Link to Source","source_url_3":"Link to source","source_url_text_4":"Link to source","source_url_text_5":"Link to source","source_url_text_6":"Link to source","source_active_7":false,"source_url_text_7":"Link to source","source_active_8":false,"source_url_text_8":"Link to source","source_active_9":false,"source_url_text_9":"Link to source","title":"Untitled","graph_title":"\ubb3c \uad00\ub828 \ud611\uc815\uc744 \ub9fa\uace0 \uc788\ub294 \uc811\uacbd \uc9c0\uc5ed \ube44\uc728","computation_units":"\ud37c\uc13c\ud2b8(%)","national_data_update_url_text":"2019-09-29: see changes on GitHub","national_data_update_url":"https://github.com/kostat-sdg-kor/sdg-data/commit/301b4daa5d61a5e8c8843faafd068f2e96374688","national_metadata_update_url_text":"2021-03-30: see changes on GitHub","national_metadata_update_url":"https://github.com/kostat-sdg-kor/sdg-data/commit/8f659164e05b9797d4838fe57635ab37453ed76c","page_content":"<b> \u25b6 \ub370\uc774\ud130 \uc720\ud615: \uad6d\uc81c\uae30\uad6c\ud1b5\uacc4(2\uc720\ud615) </b>   \n  \uad6d\uc81c\uae30\uad6c\uc5d0\uc11c \ucd94\uc815 \ubc0f \ubaa8\ub378\ub9c1 \ub4f1\uc744 \ud1b5\ud574 \uc791\uc131\ud55c \ud55c\uad6d \ub370\uc774\ud130\uc785\ub2c8\ub2e4.   \n  UN SDGs \uc9c0\ud45c\uc5d0 \ub300\uc751\ud558\ub294 \uad6d\ub0b4 \ud1b5\uacc4\uac00 \uc5c6\ub294 \uacbd\uc6b0\uc5d0 \uad6d\uc81c\uae30\uad6c\ud1b5\uacc4\ub97c \ud1b5\ud574 \ubaa8\ub2c8\ud130\ub9c1 \uc911\uc785\ub2c8\ub2e4. \n"}