{"indicator":"8.10.1","layout":"indicator","permalink":"/8-10-1/","sdg_goal":"8","target_id":"8.10","published":true,"target":"\uae08\uc735\uc11c\ube44\uc2a4 \uc811\uadfc \ud655\ub300 \ubc0f \uae08\uc735\uae30\uad00 \uc5ed\ub7c9 \uac15\ud654","indicator_name":"(a) \uc131\uc778 \uc2ed\ub9cc \uba85\ub2f9 \uc0c1\uc5c5\uc740\ud589 \uc9c0\uc810\ub4e4\uacfc (b) \uc131\uc778 \uc2ed\ub9cc \uba85\ub2f9 ATM\uc758 \uac1c\uc218","indicator_definition":"\uc131\uc778 10\ub9cc \uba85 \ub2f9 \uc0c1\uc5c5\uc740\ud589 \uc9c0\uc810 \uc218\uc640 ATM \uc218","un_designated_tier":"I","un_custodian_agency":"International Monetary Fund (IMF)","goal_meta_link":"https://unstats.un.org/sdgs/metadata/files/Metadata-08-10-01.pdf","goal_meta_link_text":"https://unstats.un.org/sdgs/metadata/files/Metadata-08-10-01.pdf","goal_meta_local_link":"https://kostat-sdg-kor.github.io/sdg-indicators/public/data/Metadata-08-10-01_KOR.pdf","goal_meta_local_link_text":"https://kostat-sdg-kor.github.io/sdg-indicators/public/data/Metadata-08-10-01_KOR.pdf","national_geographical_coverage":"\uc804\uad6d","computation_units":"\uc131\uc778 100,000\uba85\ub2f9 \uba85","reporting_status":"complete","data_non_statistical":false,"graph_type":"line","graph_title":"\uc131\uc778 10\ub9cc \uba85 \ub2f9 \uc0c1\uc5c5\uc740\ud589 \uc9c0\uc810 \uc218 / \uc131\uc778 10\ub9cc \uba85 \ub2f9 ATM \uc218","data_show_map":false,"source_active_1":false,"source_organisation_1":"LINK","source_periodicity_1":"Annual","source_earliest_available_1":"1998","source_geographical_coverage_1":"UK","source_url_1":"https://www.link.co.uk/about/statistics-and-trends/","source_url_text_1":"LINK ATM Numbers (thousands)","source_release_date_1":"N/A","source_next_release_1":"N/A","source_statistical_classification_1":"Non-official","source_contact_1":"https://www.link.co.uk/contact-us/","source_active_2":false,"source_active_3":false,"source_active_4":false,"source_active_5":false,"source_active_6":false,"indicator_sort_order":"08-10-01","source_url_text_2":"Link to Source","source_url_3":"Link to source","source_url_text_4":"Link to source","source_url_text_5":"Link to source","source_url_text_6":"Link to source","source_active_7":false,"source_url_text_7":"Link to source","source_active_8":false,"source_url_text_8":"Link to source","source_active_9":false,"source_url_text_9":"Link to source","title":"Untitled","national_data_update_url_text":"2020-07-27: see changes on GitHub","national_data_update_url":"https://github.com/kostat-sdg-kor/sdg-data/commit/58309a3d6c8cc6b11fa509a5e7332fc2cca395ca","national_metadata_update_url_text":"2020-12-02: see changes on GitHub","national_metadata_update_url":"https://github.com/kostat-sdg-kor/sdg-data/commit/f8dd7fb2951c23192574df5a734dcb2b0ae5df0c","page_content":"<b> \u25b6 \ub370\uc774\ud130 \uc720\ud615: \uad6d\uc81c\uae30\uad6c\ud1b5\uacc4(2\uc720\ud615) </b>   \n  \uad6d\uc81c\uae30\uad6c\uc5d0\uc11c \ucd94\uc815 \ubc0f \ubaa8\ub378\ub9c1 \ub4f1\uc744 \ud1b5\ud574 \uc791\uc131\ud55c \ud55c\uad6d \ub370\uc774\ud130\uc785\ub2c8\ub2e4.   \n  UN SDGs \uc9c0\ud45c\uc5d0 \ub300\uc751\ud558\ub294 \uad6d\ub0b4 \ud1b5\uacc4\uac00 \uc5c6\ub294 \uacbd\uc6b0\uc5d0 \uad6d\uc81c\uae30\uad6c\ud1b5\uacc4\ub97c \ud1b5\ud574 \ubaa8\ub2c8\ud130\ub9c1 \uc911\uc785\ub2c8\ub2e4. \n"}