[{"Year":2000,"Value":43.76},{"Year":2001,"Value":-38.2},{"Year":2002,"Value":1595.15},{"Year":2003,"Value":2181.46},{"Year":2004,"Value":3153.02},{"Year":2005,"Value":4909.85},{"Year":2006,"Value":6514.24},{"Year":2007,"Value":11581.91},{"Year":2008,"Value":10700.1},{"Year":2009,"Value":6442.31},{"Year":2010,"Value":11834.07},{"Year":2011,"Value":11508.67},{"Year":2012,"Value":12414.91},{"Year":2013,"Value":15038.36},{"Year":2014,"Value":11648.8},{"Year":2015,"Value":12318.16},{"Year":2016,"Value":12222.24},{"Year":2017,"Value":10882.47},{"Year":2018,"Value":12614.56},{"Year":2019,"Value":12161.75},{"Year":2020,"Value":12201.03},{"Year":2021,"Value":2986.61}]