[{"Year":2000,"Value":15.56642,"Units":"1\uc778\ub2f9 \uad6d\ub0b4\ubb3c\uc9c8\uc18c\ube44\ub7c9(\ud1a4)"},{"Year":2001,"Value":15.9449,"Units":"1\uc778\ub2f9 \uad6d\ub0b4\ubb3c\uc9c8\uc18c\ube44\ub7c9(\ud1a4)"},{"Year":2002,"Value":16.27433,"Units":"1\uc778\ub2f9 \uad6d\ub0b4\ubb3c\uc9c8\uc18c\ube44\ub7c9(\ud1a4)"},{"Year":2003,"Value":17.17376,"Units":"1\uc778\ub2f9 \uad6d\ub0b4\ubb3c\uc9c8\uc18c\ube44\ub7c9(\ud1a4)"},{"Year":2004,"Value":16.74107,"Units":"1\uc778\ub2f9 \uad6d\ub0b4\ubb3c\uc9c8\uc18c\ube44\ub7c9(\ud1a4)"},{"Year":2005,"Value":14.96219,"Units":"1\uc778\ub2f9 \uad6d\ub0b4\ubb3c\uc9c8\uc18c\ube44\ub7c9(\ud1a4)"},{"Year":2006,"Value":15.31776,"Units":"1\uc778\ub2f9 \uad6d\ub0b4\ubb3c\uc9c8\uc18c\ube44\ub7c9(\ud1a4)"},{"Year":2007,"Value":15.83154,"Units":"1\uc778\ub2f9 \uad6d\ub0b4\ubb3c\uc9c8\uc18c\ube44\ub7c9(\ud1a4)"},{"Year":2008,"Value":16.04899,"Units":"1\uc778\ub2f9 \uad6d\ub0b4\ubb3c\uc9c8\uc18c\ube44\ub7c9(\ud1a4)"},{"Year":2009,"Value":15.57476,"Units":"1\uc778\ub2f9 \uad6d\ub0b4\ubb3c\uc9c8\uc18c\ube44\ub7c9(\ud1a4)"},{"Year":2010,"Value":15.72987,"Units":"1\uc778\ub2f9 \uad6d\ub0b4\ubb3c\uc9c8\uc18c\ube44\ub7c9(\ud1a4)"},{"Year":2011,"Value":15.48378,"Units":"1\uc778\ub2f9 \uad6d\ub0b4\ubb3c\uc9c8\uc18c\ube44\ub7c9(\ud1a4)"},{"Year":2012,"Value":16.16143,"Units":"1\uc778\ub2f9 \uad6d\ub0b4\ubb3c\uc9c8\uc18c\ube44\ub7c9(\ud1a4)"},{"Year":2013,"Value":16.45324,"Units":"1\uc778\ub2f9 \uad6d\ub0b4\ubb3c\uc9c8\uc18c\ube44\ub7c9(\ud1a4)"},{"Year":2014,"Value":16.49969,"Units":"1\uc778\ub2f9 \uad6d\ub0b4\ubb3c\uc9c8\uc18c\ube44\ub7c9(\ud1a4)"},{"Year":2015,"Value":17.25191,"Units":"1\uc778\ub2f9 \uad6d\ub0b4\ubb3c\uc9c8\uc18c\ube44\ub7c9(\ud1a4)"},{"Year":2016,"Value":18.26477,"Units":"1\uc778\ub2f9 \uad6d\ub0b4\ubb3c\uc9c8\uc18c\ube44\ub7c9(\ud1a4)"},{"Year":2017,"Value":18.58578,"Units":"1\uc778\ub2f9 \uad6d\ub0b4\ubb3c\uc9c8\uc18c\ube44\ub7c9(\ud1a4)"},{"Year":2018,"Value":18.22295,"Units":"1\uc778\ub2f9 \uad6d\ub0b4\ubb3c\uc9c8\uc18c\ube44\ub7c9(\ud1a4)"},{"Year":2019,"Value":17.96787,"Units":"1\uc778\ub2f9 \uad6d\ub0b4\ubb3c\uc9c8\uc18c\ube44\ub7c9(\ud1a4)"},{"Year":2000,"Value":0.92331,"Units":"data.Kilograms_per_constant_2015_USD"},{"Year":2001,"Value":0.90822,"Units":"data.Kilograms_per_constant_2015_USD"},{"Year":2002,"Value":0.8658,"Units":"data.Kilograms_per_constant_2015_USD"},{"Year":2003,"Value":0.89059,"Units":"data.Kilograms_per_constant_2015_USD"},{"Year":2004,"Value":0.82924,"Units":"data.Kilograms_per_constant_2015_USD"},{"Year":2005,"Value":0.71355,"Units":"data.Kilograms_per_constant_2015_USD"},{"Year":2006,"Value":0.69653,"Units":"data.Kilograms_per_constant_2015_USD"},{"Year":2007,"Value":0.68258,"Units":"data.Kilograms_per_constant_2015_USD"},{"Year":2008,"Value":0.67374,"Units":"data.Kilograms_per_constant_2015_USD"},{"Year":2009,"Value":0.65087,"Units":"data.Kilograms_per_constant_2015_USD"},{"Year":2010,"Value":0.61794,"Units":"data.Kilograms_per_constant_2015_USD"},{"Year":2011,"Value":0.5895,"Units":"data.Kilograms_per_constant_2015_USD"},{"Year":2012,"Value":0.60417,"Units":"data.Kilograms_per_constant_2015_USD"},{"Year":2013,"Value":0.59961,"Units":"data.Kilograms_per_constant_2015_USD"},{"Year":2014,"Value":0.58568,"Units":"data.Kilograms_per_constant_2015_USD"},{"Year":2015,"Value":0.59818,"Units":"data.Kilograms_per_constant_2015_USD"},{"Year":2016,"Value":0.61711,"Units":"data.Kilograms_per_constant_2015_USD"},{"Year":2017,"Value":0.61007,"Units":"data.Kilograms_per_constant_2015_USD"},{"Year":2018,"Value":0.58212,"Units":"data.Kilograms_per_constant_2015_USD"},{"Year":2019,"Value":0.56309,"Units":"data.Kilograms_per_constant_2015_USD"},{"Year":2000,"Value":737525100.1310100555,"Units":"\uad6d\ub0b4\ubb3c\uc9c8\uc18c\ube44\ub7c9(\ud1a4)"},{"Year":2001,"Value":760671137.8490099907,"Units":"\uad6d\ub0b4\ubb3c\uc9c8\uc18c\ube44\ub7c9(\ud1a4)"},{"Year":2002,"Value":781160332.7041200399,"Units":"\uad6d\ub0b4\ubb3c\uc9c8\uc18c\ube44\ub7c9(\ud1a4)"},{"Year":2003,"Value":828820891.9005099535,"Units":"\uad6d\ub0b4\ubb3c\uc9c8\uc18c\ube44\ub7c9(\ud1a4)"},{"Year":2004,"Value":811832152.1142300367,"Units":"\uad6d\ub0b4\ubb3c\uc9c8\uc18c\ube44\ub7c9(\ud1a4)"},{"Year":2005,"Value":728674783.9971200228,"Units":"\uad6d\ub0b4\ubb3c\uc9c8\uc18c\ube44\ub7c9(\ud1a4)"},{"Year":2006,"Value":748738938.1205999851,"Units":"\uad6d\ub0b4\ubb3c\uc9c8\uc18c\ube44\ub7c9(\ud1a4)"},{"Year":2007,"Value":776296395.4224300385,"Units":"\uad6d\ub0b4\ubb3c\uc9c8\uc18c\ube44\ub7c9(\ud1a4)"},{"Year":2008,"Value":789328578.8169699907,"Units":"\uad6d\ub0b4\ubb3c\uc9c8\uc18c\ube44\ub7c9(\ud1a4)"},{"Year":2009,"Value":768574775.0705200434,"Units":"\uad6d\ub0b4\ubb3c\uc9c8\uc18c\ube44\ub7c9(\ud1a4)"},{"Year":2010,"Value":779346277.0813000202,"Units":"\uad6d\ub0b4\ubb3c\uc9c8\uc18c\ube44\ub7c9(\ud1a4)"},{"Year":2011,"Value":770877863.1924300194,"Units":"\uad6d\ub0b4\ubb3c\uc9c8\uc18c\ube44\ub7c9(\ud1a4)"},{"Year":2012,"Value":809051555.5590000153,"Units":"\uad6d\ub0b4\ubb3c\uc9c8\uc18c\ube44\ub7c9(\ud1a4)"},{"Year":2013,"Value":828350448.5849000216,"Units":"\uad6d\ub0b4\ubb3c\uc9c8\uc18c\ube44\ub7c9(\ud1a4)"},{"Year":2014,"Value":835014649.9978699684,"Units":"\uad6d\ub0b4\ubb3c\uc9c8\uc18c\ube44\ub7c9(\ud1a4)"},{"Year":2015,"Value":876795357.6879700422,"Units":"\uad6d\ub0b4\ubb3c\uc9c8\uc18c\ube44\ub7c9(\ud1a4)"},{"Year":2016,"Value":931200941.9850100279,"Units":"\uad6d\ub0b4\ubb3c\uc9c8\uc18c\ube44\ub7c9(\ud1a4)"},{"Year":2017,"Value":949666842.9578000307,"Units":"\uad6d\ub0b4\ubb3c\uc9c8\uc18c\ube44\ub7c9(\ud1a4)"},{"Year":2018,"Value":932499258.9395400286,"Units":"\uad6d\ub0b4\ubb3c\uc9c8\uc18c\ube44\ub7c9(\ud1a4)"},{"Year":2019,"Value":920410002.5840200186,"Units":"\uad6d\ub0b4\ubb3c\uc9c8\uc18c\ube44\ub7c9(\ud1a4)"}]